ackeras/__init__.py
ackeras/classification.py
ackeras/clustering.py
ackeras/data_cleaning.py
ackeras/data_viz.py
ackeras/dim_red.py
ackeras/outlier_detection.py
ackeras/pipeline.py
ackeras/regression.py
ackeras-0.1.0.dist-info/METADATA
ackeras-0.1.0.dist-info/RECORD
ackeras-0.1.0.dist-info/WHEEL
ackeras-0.1.0.dist-info/top_level.txt
