Metadata-Version: 2.1
Name: ackeras
Version: 0.1.0
Summary: Simple wrapper around Sklearn and Autokeras
Home-page: https://github.com/accurat/ackeras
Author: Andrea Titton
Author-email: andrea.titton@accurat.it
License: UNKNOWN
Keywords: autoML
Platform: UNKNOWN
